occamypy/__init__.py
occamypy/__version__.py
occamypy/cupy/__init__.py
occamypy/cupy/vector.py
occamypy/cupy/operator/__init__.py
occamypy/cupy/operator/signal.py
occamypy/dask/__init__.py
occamypy/dask/operator.py
occamypy/dask/utils.py
occamypy/dask/vector.py
occamypy/numpy/__init__.py
occamypy/numpy/vector.py
occamypy/numpy/operator/__init__.py
occamypy/numpy/operator/pylops_interface.py
occamypy/numpy/operator/signal.py
occamypy/numpy/operator/transform.py
occamypy/operator/__init__.py
occamypy/operator/base.py
occamypy/operator/derivative.py
occamypy/operator/linear.py
occamypy/operator/matrix.py
occamypy/operator/nonlinear.py
occamypy/operator/signal.py
occamypy/problem/__init__.py
occamypy/problem/base.py
occamypy/problem/linear.py
occamypy/problem/nonlinear.py
occamypy/solver/__init__.py
occamypy/solver/base.py
occamypy/solver/linear.py
occamypy/solver/mcmc.py
occamypy/solver/nonlinear.py
occamypy/solver/sparsity.py
occamypy/solver/stepper.py
occamypy/solver/stopper.py
occamypy/torch/__init__.py
occamypy/torch/autograd.py
occamypy/torch/back_utils.py
occamypy/torch/vector.py
occamypy/torch/operator/__init__.py
occamypy/torch/operator/signal.py
occamypy/torch/operator/transform.py
occamypy/utils/__init__.py
occamypy/utils/backend.py
occamypy/utils/logger.py
occamypy/utils/os.py
occamypy/utils/plot.py
occamypy/utils/sep.py
occamypy/vector/__init__.py
occamypy/vector/axis_info.py
occamypy/vector/base.py
occamypy/vector/out_core.py
occamypy-0.2.0.dist-info/LICENSE.md
occamypy-0.2.0.dist-info/METADATA
occamypy-0.2.0.dist-info/WHEEL
occamypy-0.2.0.dist-info/top_level.txt
occamypy-0.2.0.dist-info/zip-safe
occamypy-0.2.0.dist-info/RECORD
