Metadata-Version: 2.1
Name: occamypy
Version: 0.2.0
Summary: An Object-Oriented Optimization Framework for Large-Scale Inverse Problems
Home-page: https://github.com/fpicetti/occamypy
Author: Ettore Biondi, Guillame Barnier, Robert Clapp, Francesco Picetti, Stuart Farris
Author-email: francesco.picetti@polimi.it
License: UNKNOWN
Keywords: algebra,inverse problems,large-scale optimization
Platform: UNKNOWN
Classifier: Development Status :: 4 - Beta
Classifier: Intended Audience :: Developers
Classifier: Intended Audience :: Science/Research
Classifier: Natural Language :: English
Classifier: Programming Language :: Python :: 3.6
Classifier: Programming Language :: Python :: 3.7
Classifier: Programming Language :: Python :: 3.8
Classifier: Topic :: Scientific/Engineering :: Mathematics
Classifier: Operating System :: Unix
License-File: LICENSE.md
Requires-Dist: numpy
Requires-Dist: scipy
Requires-Dist: numba
Requires-Dist: torch (>=1.7.0)
Requires-Dist: dask
Requires-Dist: dask-jobqueue
Requires-Dist: dask-kubernetes
Requires-Dist: matplotlib
Requires-Dist: gputil
Requires-Dist: imageio
